zxarray/__DMUnit.py
zxarray/__ZXArray.py
zxarray/__apply_ufunc.py
zxarray/__init__.py
zxarray/__release.py
zxarray/__stats.py
zxarray/__sys.py
zxarray/__zxParams.py
zxarray-0.13.4.dist-info/licenses/LICENSE
zxarray-0.13.4.dist-info/METADATA
zxarray-0.13.4.dist-info/WHEEL
zxarray-0.13.4.dist-info/top_level.txt
zxarray-0.13.4.dist-info/RECORD
