Metadata-Version: 2.4
Name: zxarray
Version: 0.13.4
Home-page: https://github.com/yrobink/zxarray
Author: Yoann Robin
Author-email: Yoann Robin <yoann.robin.k@gmail.com>
Maintainer-email: Yoann Robin <yoann.robin.k@gmail.com>
License-Expression: GPL-3.0-or-later
Platform: linux
Platform: macosx
Classifier: Development Status :: 5 - Production/Stable
Classifier: Natural Language :: English
Classifier: Operating System :: MacOS :: MacOS X
Classifier: Operating System :: POSIX :: Linux
Classifier: Programming Language :: Python :: 3
Classifier: Topic :: Scientific/Engineering :: Mathematics
Classifier: Intended Audience :: Science/Research
Requires: numpy
Requires: xarray
Requires: zarr(>=3.1.0)
Requires: netCDF4
Requires: cftime
Requires-Python: >=3.10
License-File: LICENSE
Requires-Dist: numpy
Requires-Dist: xarray
Requires-Dist: zarr>=3.1.0
Requires-Dist: netCDF4
Requires-Dist: cftime
Dynamic: author
Dynamic: home-page
Dynamic: license-file
Dynamic: platform
Dynamic: requires
